drf_openapi3/__init__.py
drf_openapi3/admin.py
drf_openapi3/apps.py
drf_openapi3/models.py
drf_openapi3/settings.py
drf_openapi3/migrations/__init__.py
drf_openapi3/schemas/__init__.py
drf_openapi3/schemas/advanced.py
drf_openapi3/schemas/generators.py
drf_openapi3/schemas/inspectors.py
drf_openapi3/schemas/openapi.py
drf_openapi3/schemas/utils.py
drf_openapi3/templates/drf_openapi3/openapi-ui.html
drf_openapi3/views/__init__.py
drf_openapi3/views/openapi_template_view.py
drf_openapi3-0.1.25.dist-info/LICENSE
drf_openapi3-0.1.25.dist-info/METADATA
drf_openapi3-0.1.25.dist-info/WHEEL
drf_openapi3-0.1.25.dist-info/top_level.txt
drf_openapi3-0.1.25.dist-info/RECORD
