Metadata-Version: 2.1
Name: drf-openapi3
Version: 0.1.25
Summary: Manage OpenApi documentation with DRF
Home-page: https://github.com/gungnir888/drf-openapi
Author: Davide Pugliese
Author-email: davide.pglse@gmail.com
License: GPL
Keywords: openapi,openapi-3.0,django-rest-framework,drf,documentatation
Platform: UNKNOWN
Classifier: Development Status :: 4 - Beta
Classifier: Environment :: Web Environment
Classifier: Framework :: Django
Classifier: Intended Audience :: Developers
Classifier: Natural Language :: English
Classifier: Operating System :: OS Independent
Classifier: Programming Language :: Python
Classifier: Programming Language :: Python :: 3 :: Only
Classifier: Programming Language :: Python :: 3.6
Classifier: Programming Language :: Python :: 3.7
Classifier: Programming Language :: Python :: 3.8
Classifier: Topic :: Software Development :: Libraries :: Python Modules
Requires-Python: >3.6.0
Requires-Dist: Django
Requires-Dist: djangorestframework
Requires-Dist: pyyaml
